<?xml version="1.0" encoding="UTF-8"?>
<InterchangeDescriptors xmlns="http://ed-fi.org/0120" xmlns:xsi="http://www.w3.org/2001/XMLSchema-instance" xsi:schemaLocation="http://ed-fi.org/0120 
..\..\..\Schemas\Interchange-Descriptors.xsd">
	<EmploymentStatusDescriptor namespace="http://www.ed-fi.org/Descriptor/EmploymentStatusDescriptor.xml">
		<ShortDescription>Probationary</ShortDescription>
		<Description>Probationary</Description>
		<EmploymentStatusMap>Probationary</EmploymentStatusMap>
	</EmploymentStatusDescriptor>
	<EmploymentStatusDescriptor namespace="http://www.ed-fi.org/Descriptor/EmploymentStatusDescriptor.xml">
		<ShortDescription>Contractual</ShortDescription>
		<Description>Contractual</Description>
		<EmploymentStatusMap>Contractual</EmploymentStatusMap>
	</EmploymentStatusDescriptor>
	<EmploymentStatusDescriptor namespace="http://www.ed-fi.org/Descriptor/EmploymentStatusDescriptor.xml">
		<ShortDescription>Employed or affiliated with outside agency part-time</ShortDescription>
		<Description>Employed or affiliated with outside agency part-time</Description>
		<EmploymentStatusMap>Employed or affiliated with outside agency part-time</EmploymentStatusMap>
	</EmploymentStatusDescriptor>
	<EmploymentStatusDescriptor namespace="http://www.ed-fi.org/Descriptor/EmploymentStatusDescriptor.xml">
		<ShortDescription>Employed or affiliated with outside organization</ShortDescription>
		<Description>Employed or affiliated with outside organization</Description>
		<EmploymentStatusMap>Employed or affiliated with outside organization</EmploymentStatusMap>
	</EmploymentStatusDescriptor>
	<EmploymentStatusDescriptor namespace="http://www.ed-fi.org/Descriptor/EmploymentStatusDescriptor.xml">
		<ShortDescription>Employed part-time</ShortDescription>
		<Description>Employed part-time</Description>
		<EmploymentStatusMap>Employed part-time</EmploymentStatusMap>
	</EmploymentStatusDescriptor>
	<EmploymentStatusDescriptor namespace="http://www.ed-fi.org/Descriptor/EmploymentStatusDescriptor.xml">
		<ShortDescription>Non-contractual</ShortDescription>
		<Description>Non-contractual</Description>
		<EmploymentStatusMap>Non-contractual</EmploymentStatusMap>
	</EmploymentStatusDescriptor>
	<EmploymentStatusDescriptor namespace="http://www.ed-fi.org/Descriptor/EmploymentStatusDescriptor.xml">
		<ShortDescription>Other</ShortDescription>
		<Description>Other</Description>
		<EmploymentStatusMap>Other</EmploymentStatusMap>
	</EmploymentStatusDescriptor>
	<EmploymentStatusDescriptor namespace="http://www.ed-fi.org/Descriptor/EmploymentStatusDescriptor.xml">
		<ShortDescription>Substitute/temporary</ShortDescription>
		<Description>Substitute/temporary</Description>
		<EmploymentStatusMap>Substitute/temporary</EmploymentStatusMap>
	</EmploymentStatusDescriptor>
	<EmploymentStatusDescriptor namespace="http://www.ed-fi.org/Descriptor/EmploymentStatusDescriptor.xml">
		<ShortDescription>Tenured or permanent</ShortDescription>
		<Description>Tenured or permanent</Description>
		<EmploymentStatusMap>Tenured or permanent</EmploymentStatusMap>
	</EmploymentStatusDescriptor>
	<EmploymentStatusDescriptor namespace="http://www.ed-fi.org/Descriptor/EmploymentStatusDescriptor.xml">
		<ShortDescription>Volunteer/no contract</ShortDescription>
		<Description>Volunteer/no contract</Description>
		<EmploymentStatusMap>Volunteer/no contract</EmploymentStatusMap>
	</EmploymentStatusDescriptor>
</InterchangeDescriptors>
